json2table/__init__.py
json2table/json2table.py
json2table-1.1.5.dist-info/DESCRIPTION.rst
json2table-1.1.5.dist-info/METADATA
json2table-1.1.5.dist-info/RECORD
json2table-1.1.5.dist-info/WHEEL
json2table-1.1.5.dist-info/metadata.json
json2table-1.1.5.dist-info/top_level.txt
