Metadata-Version: 1.1
Name: json2table
Version: 1.1.5
Summary: Convert JSON to an HTML table
Home-page: https://github.com/latture/json2table
Author: Ryan Latture
Author-email: ryan.latture@gmail.com
License: MIT
Download-URL: https://github.com/latture/json2table/tarball/master
Keywords: json,HTML,convert,table
Platform: UNKNOWN
Classifier: Programming Language :: Python
Classifier: Programming Language :: Python :: 2
Classifier: Programming Language :: Python :: 3
Classifier: License :: OSI Approved :: MIT License
